{"openapi":"3.1.0","info":{"title":"PKKA Backend API","description":"REST API for the Alumni Club platform of the AGH Faculty of Computer Science.","version":"v1"},"servers":[{"url":"http://localhost:8080","description":"Local dev"}],"tags":[{"name":"Profiles","description":"Own user profile management — requires USER role"},{"name":"Posts","description":"Public posts on the faculty blog"},{"name":"Admin Applications","description":"Reviewer actions on alumnus applications"},{"name":"Tags","description":"Available skill tags — requires USER role"},{"name":"Applications","description":"Alumnus applications submitted by the logged-in user"},{"name":"Events","description":"Public events calendar"},{"name":"Me","description":"Current user identity and roles"}],"paths":{"/api/profiles/me/tags":{"get":{"tags":["Profiles"],"summary":"Get own assigned tags","operationId":"getMyTags","responses":{"200":{"description":"OK","content":{"*/*":{"schema":{"type":"array","items":{"$ref":"#/components/schemas/TagResponse"}}}}}}},"put":{"tags":["Profiles"],"summary":"Replace own tags (full replacement of the assigned set)","operationId":"updateMyTags","requestBody":{"content":{"application/json":{"schema":{"$ref":"#/components/schemas/UpdateTagsRequest"}}},"required":true},"responses":{"200":{"description":"OK","content":{"*/*":{"schema":{"type":"array","items":{"$ref":"#/components/schemas/TagResponse"}}}}},"400":{"description":"One or more tag IDs do not exist","content":{"*/*":{"schema":{"$ref":"#/components/schemas/ProblemDetail"}}}}}}},"/api/public/auth/refresh":{"post":{"tags":["auth-refresh-controller"],"operationId":"refresh","requestBody":{"content":{"application/json":{"schema":{"$ref":"#/components/schemas/RefreshRequest"}}},"required":true},"responses":{"200":{"description":"OK","content":{"*/*":{"schema":{"$ref":"#/components/schemas/TokenResponse"}}}}}}},"/api/public/auth/logout":{"post":{"tags":["auth-refresh-controller"],"operationId":"logout","requestBody":{"content":{"application/json":{"schema":{"$ref":"#/components/schemas/RefreshRequest"}}},"required":true},"responses":{"204":{"description":"No Content"}}}},"/api/applications":{"post":{"tags":["Applications"],"summary":"Submit an alumnus application for the current user","operationId":"createApplication","requestBody":{"content":{"application/json":{"schema":{"$ref":"#/components/schemas/CreateApplicationRequestDto"}}},"required":true},"responses":{"201":{"description":"Application created","content":{"*/*":{"schema":{"$ref":"#/components/schemas/ApplicationResponseDto"}}}},"400":{"description":"Validation failed"},"409":{"description":"The user already has an application under review"}}}},"/api/admin/applications/{id}/reject":{"post":{"tags":["Admin Applications"],"summary":"Reject an application with an optional reason","operationId":"reject","parameters":[{"name":"id","in":"path","required":true,"schema":{"type":"string","format":"uuid"}}],"requestBody":{"content":{"application/json":{"schema":{"$ref":"#/components/schemas/RejectApplicationRequestDto"}}}},"responses":{"200":{"description":"Application rejected","content":{"*/*":{"schema":{"$ref":"#/components/schemas/ApplicationResponseDto"}}}},"404":{"description":"Application not found"},"409":{"description":"Application is not under review"}}}},"/api/admin/applications/{id}/approve":{"post":{"tags":["Admin Applications"],"summary":"Approve an application and grant the verified alumn role","operationId":"approve","parameters":[{"name":"id","in":"path","required":true,"schema":{"type":"string","format":"uuid"}}],"responses":{"200":{"description":"Application approved","content":{"*/*":{"schema":{"$ref":"#/components/schemas/ApplicationResponseDto"}}}},"404":{"description":"Application not found"},"409":{"description":"Application is not under review"}}}},"/api/profiles/me":{"get":{"tags":["Profiles"],"summary":"Get own profile","operationId":"getMyProfile","responses":{"200":{"description":"OK","content":{"*/*":{"schema":{"$ref":"#/components/schemas/ProfileResponse"}}}}}},"patch":{"tags":["Profiles"],"summary":"Update own profile","description":"Partial update: null or omitted fields clear the stored value","operationId":"updateMyProfile","requestBody":{"content":{"application/json":{"schema":{"$ref":"#/components/schemas/UpdateProfileRequest"}}},"required":true},"responses":{"200":{"description":"OK","content":{"*/*":{"schema":{"$ref":"#/components/schemas/ProfileResponse"}}}}}}},"/debug/token":{"get":{"tags":["debug-token-controller"],"operationId":"debugToken","responses":{"200":{"description":"OK","content":{"*/*":{"schema":{"type":"array","items":{"type":"object","additionalProperties":{}}}}}}}}},"/api/tags":{"get":{"tags":["Tags"],"summary":"List all available skill tags","operationId":"listTags","responses":{"200":{"description":"OK","content":{"*/*":{"schema":{"type":"array","items":{"$ref":"#/components/schemas/TagResponse"}}}}}}}},"/api/public/posts":{"get":{"tags":["Posts"],"summary":"List of published posts","description":"Available without authentication. Posts are ordered from newest to oldest.\nPagination parameters: page (default 0), size (default 10).\n","operationId":"listPosts","parameters":[{"name":"page","in":"query","description":"Zero-based page index (0..N)","required":false,"schema":{"type":"integer","default":0,"minimum":0}},{"name":"size","in":"query","description":"The size of the page to be returned","required":false,"schema":{"type":"integer","default":10,"minimum":1}},{"name":"sort","in":"query","description":"Sorting criteria in the format: property,(asc|desc). Default sort order is ascending. Multiple sort criteria are supported.","required":false,"schema":{"type":"array","items":{"type":"string"}}}],"responses":{"200":{"description":"OK","content":{"*/*":{"schema":{"$ref":"#/components/schemas/PagePostSummaryResponse"}}}}}}},"/api/public/posts/{slug}":{"get":{"tags":["Posts"],"summary":"Single post by slug","description":"Available without authentication. Returns 404 if the post does not exist or is a draft.","operationId":"getPost","parameters":[{"name":"slug","in":"path","required":true,"schema":{"type":"string"}}],"responses":{"200":{"description":"OK","content":{"*/*":{"schema":{"$ref":"#/components/schemas/PostResponse"}}}},"404":{"description":"Post does not exist or is not published"}}}},"/api/public/events":{"get":{"tags":["Events"],"summary":"List of upcoming events (optional filtering by tags)","operationId":"listEvents","parameters":[{"name":"tags","in":"query","required":false,"schema":{"type":"array","items":{"type":"string"},"uniqueItems":true}},{"name":"page","in":"query","description":"Zero-based page index (0..N)","required":false,"schema":{"type":"integer","default":0,"minimum":0}},{"name":"size","in":"query","description":"The size of the page to be returned","required":false,"schema":{"type":"integer","default":20,"minimum":1}},{"name":"sort","in":"query","description":"Sorting criteria in the format: property,(asc|desc). Default sort order is ascending. Multiple sort criteria are supported.","required":false,"schema":{"type":"array","default":["startsAt,ASC"],"items":{"type":"string"}}}],"responses":{"200":{"description":"OK","content":{"*/*":{"schema":{"$ref":"#/components/schemas/PageEventListItemDto"}}}}}}},"/api/public/events/{id}":{"get":{"tags":["Events"],"summary":"Details of a single event","operationId":"getEventById","parameters":[{"name":"id","in":"path","required":true,"schema":{"type":"string","format":"uuid"}}],"responses":{"200":{"description":"OK","content":{"*/*":{"schema":{"$ref":"#/components/schemas/EventDetailsDto"}}}}}}},"/api/public/auth/post-logout":{"get":{"tags":["web-logout-redirect-controller"],"operationId":"postLogout","responses":{"200":{"description":"OK"}}}},"/api/me":{"get":{"tags":["Me"],"summary":"Current user info","description":"Returns identity claims and realm roles for the currently authenticated user.\nWorks for both web (OIDC session) and mobile (Bearer JWT) flows.\nRoles are returned without the ROLE_ prefix.\n","operationId":"me","responses":{"200":{"description":"OK","content":{"*/*":{"schema":{"$ref":"#/components/schemas/MeResponse"}}}}}}},"/api/applications/me":{"get":{"tags":["Applications"],"summary":"Get the current user's application","operationId":"getMine","responses":{"200":{"description":"The user's most recent application","content":{"*/*":{"schema":{"$ref":"#/components/schemas/ApplicationResponseDto"}}}},"404":{"description":"The user has no application"}}}},"/api/admin/applications":{"get":{"tags":["Admin Applications"],"summary":"List applications with full details, filtered by status (newest first)","operationId":"listAdminApplications","parameters":[{"name":"status","in":"query","required":false,"schema":{"type":"string","default":"UNDER_REVIEW","enum":["UNDER_REVIEW","APPROVED","REJECTED"]}},{"name":"page","in":"query","description":"Zero-based page index (0..N)","required":false,"schema":{"type":"integer","default":0,"minimum":0}},{"name":"size","in":"query","description":"The size of the page to be returned","required":false,"schema":{"type":"integer","default":20,"minimum":1}},{"name":"sort","in":"query","description":"Sorting criteria in the format: property,(asc|desc). Default sort order is ascending. Multiple sort criteria are supported.","required":false,"schema":{"type":"array","items":{"type":"string"}}}],"responses":{"200":{"description":"OK","content":{"*/*":{"schema":{"$ref":"#/components/schemas/PageAdminApplicationResponseDto"}}}}}}},"/api/admin/applications/{id}":{"get":{"tags":["Admin Applications"],"summary":"Get full details of a single application","operationId":"getAdminApplication","parameters":[{"name":"id","in":"path","required":true,"schema":{"type":"string","format":"uuid"}}],"responses":{"200":{"description":"Application details","content":{"*/*":{"schema":{"$ref":"#/components/schemas/AdminApplicationResponseDto"}}}},"404":{"description":"Application not found"}}}}},"components":{"schemas":{"UpdateTagsRequest":{"type":"object","properties":{"tagIds":{"type":"array","description":"Full replacement set of tag IDs","items":{"type":"string","format":"uuid"},"maxItems":20,"minItems":0,"uniqueItems":true}},"required":["tagIds"]},"ProblemDetail":{"type":"object","properties":{"type":{"type":"string","format":"uri"},"title":{"type":"string"},"status":{"type":"integer","format":"int32"},"detail":{"type":"string"},"instance":{"type":"string","format":"uri"},"properties":{"type":"object","additionalProperties":{}}}},"TagResponse":{"type":"object","properties":{"id":{"type":"string","format":"uuid"},"name":{"type":"string"}},"required":["id","name"]},"RefreshRequest":{"type":"object","properties":{"refreshToken":{"type":"string"}}},"TokenResponse":{"type":"object","properties":{"access_token":{"type":"string"},"refresh_token":{"type":"string"}}},"CreateApplicationRequestDto":{"type":"object","properties":{"faculty":{"type":"string","description":"AGH faculty code","enum":["WE","WEGH","WEAIE","WEAIIE","WIET","WI"],"example":"WI"},"fieldOfStudy":{"type":"string","description":"Field of study","example":"Informatyka","maxLength":200,"minLength":0},"studyType":{"type":"string","enum":["BACHELOR","MASTER","DOCTORAL","POSTGRADUATE"]},"graduationYear":{"type":"integer","format":"int32","description":"Year of graduation","example":2020,"minimum":1919},"interests":{"type":"array","description":"Free-form areas of interest","example":["AI","backend"],"items":{"type":"string","maxLength":100,"minLength":0},"uniqueItems":true},"meetingPreferences":{"type":"array","description":"Acceptable meeting formats","items":{"type":"string","enum":["ONLINE","IN_PERSON_KRAKOW","HYBRID"]},"uniqueItems":true},"coCreationInterest":{"type":"boolean","description":"Willingness to actively co-create the club"},"newsletterSubscription":{"type":"boolean","description":"Newsletter subscription"},"phoneNumber":{"type":"string","description":"Phone number","example":"+48 123 456 789","maxLength":32,"minLength":0,"pattern":"^\\+?[0-9 \\-]{7,32}$"},"consents":{"type":"array","description":"Required consents — must include REGULATIONS_PRIVACY and GDPR_DATA_PROCESSING","items":{"type":"string","enum":["REGULATIONS_PRIVACY","GDPR_DATA_PROCESSING"]},"minItems":1,"uniqueItems":true}},"required":["consents","faculty","fieldOfStudy","graduationYear","phoneNumber","studyType"]},"ApplicationResponseDto":{"type":"object","properties":{"id":{"type":"string","format":"uuid"},"status":{"type":"string","enum":["UNDER_REVIEW","APPROVED","REJECTED"]},"faculty":{"type":"string","enum":["WE","WEGH","WEAIE","WEAIIE","WIET","WI"]},"fieldOfStudy":{"type":"string"},"studyType":{"type":"string","enum":["BACHELOR","MASTER","DOCTORAL","POSTGRADUATE"]},"graduationYear":{"type":"integer","format":"int32"},"meetingPreferences":{"type":"array","items":{"type":"string","enum":["ONLINE","IN_PERSON_KRAKOW","HYBRID"]},"uniqueItems":true},"coCreationInterest":{"type":"boolean"},"newsletterSubscription":{"type":"boolean"},"phoneNumber":{"type":"string"},"interests":{"type":"array","items":{"type":"string"},"uniqueItems":true},"consents":{"type":"array","items":{"type":"string","enum":["REGULATIONS_PRIVACY","GDPR_DATA_PROCESSING"]},"uniqueItems":true},"reviewedAt":{"type":"string","format":"date-time","description":"Set once the application is reviewed"},"rejectionReason":{"type":"string","description":"Reason supplied when the application was rejected"},"createdAt":{"type":"string","format":"date-time"},"updatedAt":{"type":"string","format":"date-time"}},"required":["coCreationInterest","consents","createdAt","faculty","fieldOfStudy","graduationYear","id","interests","meetingPreferences","newsletterSubscription","phoneNumber","status","studyType","updatedAt"]},"RejectApplicationRequestDto":{"type":"object","properties":{"reason":{"type":"string","description":"Optional reason shown to the applicant","example":"Brak udokumentowanego ukończenia studiów","maxLength":1000,"minLength":0}}},"UpdateProfileRequest":{"type":"object","description":"Fields to update; omitted or null fields clear the stored value","properties":{"currentPosition":{"type":"string","maxLength":255,"minLength":0},"company":{"type":"string","maxLength":255,"minLength":0},"linkedinUrl":{"type":"string","maxLength":500,"minLength":0},"githubUrl":{"type":"string","maxLength":500,"minLength":0}}},"ProfileResponse":{"type":"object","properties":{"id":{"type":"string","format":"uuid"},"currentPosition":{"type":"string"},"company":{"type":"string"},"linkedinUrl":{"type":"string"},"githubUrl":{"type":"string"},"tags":{"type":"array","items":{"$ref":"#/components/schemas/TagResponse"}}},"required":["id","tags"]},"PagePostSummaryResponse":{"type":"object","properties":{"totalElements":{"type":"integer","format":"int64"},"totalPages":{"type":"integer","format":"int32"},"size":{"type":"integer","format":"int32"},"content":{"type":"array","items":{"$ref":"#/components/schemas/PostSummaryResponse"}},"number":{"type":"integer","format":"int32"},"numberOfElements":{"type":"integer","format":"int32"},"pageable":{"$ref":"#/components/schemas/PageableObject"},"sort":{"$ref":"#/components/schemas/SortObject"},"first":{"type":"boolean"},"last":{"type":"boolean"},"empty":{"type":"boolean"}}},"PageableObject":{"type":"object","properties":{"offset":{"type":"integer","format":"int64"},"paged":{"type":"boolean"},"pageNumber":{"type":"integer","format":"int32"},"pageSize":{"type":"integer","format":"int32"},"sort":{"$ref":"#/components/schemas/SortObject"},"unpaged":{"type":"boolean"}}},"PostSummaryResponse":{"type":"object","properties":{"id":{"type":"string","format":"uuid"},"slug":{"type":"string"},"title":{"type":"string"},"authorId":{"type":"string"},"publishedAt":{"type":"string","format":"date-time"}},"required":["authorId","id","publishedAt","slug","title"]},"SortObject":{"type":"object","properties":{"empty":{"type":"boolean"},"sorted":{"type":"boolean"},"unsorted":{"type":"boolean"}}},"PostResponse":{"type":"object","properties":{"id":{"type":"string","format":"uuid"},"slug":{"type":"string"},"title":{"type":"string"},"content":{"type":"string"},"authorId":{"type":"string"},"publishedAt":{"type":"string","format":"date-time"},"updatedAt":{"type":"string","format":"date-time"}},"required":["authorId","content","id","publishedAt","slug","title","updatedAt"]},"EventListItemDto":{"type":"object","properties":{"id":{"type":"string","format":"uuid"},"title":{"type":"string"},"startsAt":{"type":"string","format":"date-time"},"type":{"type":"string","enum":["ONLINE","IN_PERSON","HYBRID"]},"location":{"type":"string"},"coverImageUrl":{"type":"string"},"seatLimit":{"type":"integer","format":"int32"},"seatsTaken":{"type":"integer","format":"int32"}},"required":["id","seatsTaken","startsAt","title","type"]},"PageEventListItemDto":{"type":"object","properties":{"totalElements":{"type":"integer","format":"int64"},"totalPages":{"type":"integer","format":"int32"},"size":{"type":"integer","format":"int32"},"content":{"type":"array","items":{"$ref":"#/components/schemas/EventListItemDto"}},"number":{"type":"integer","format":"int32"},"numberOfElements":{"type":"integer","format":"int32"},"pageable":{"$ref":"#/components/schemas/PageableObject"},"sort":{"$ref":"#/components/schemas/SortObject"},"first":{"type":"boolean"},"last":{"type":"boolean"},"empty":{"type":"boolean"}}},"EventDetailsDto":{"type":"object","properties":{"id":{"type":"string","format":"uuid"},"title":{"type":"string"},"fullDescription":{"type":"string"},"type":{"type":"string","enum":["ONLINE","IN_PERSON","HYBRID"]},"startsAt":{"type":"string","format":"date-time"},"endsAt":{"type":"string","format":"date-time"},"location":{"type":"string"},"seatLimit":{"type":"integer","format":"int32"},"seatsTaken":{"type":"integer","format":"int32"},"registrationClosesAt":{"type":"string","format":"date-time"},"audience":{"type":"string","enum":["PUBLIC","ALL_ALUMNI","SPECIFIC_GROUP"]},"coverImageUrl":{"type":"string"},"tags":{"type":"array","items":{"type":"string"},"uniqueItems":true}},"required":["audience","endsAt","id","seatsTaken","startsAt","tags","title","type"]},"MeResponse":{"type":"object","properties":{"sub":{"type":"string","description":"Keycloak subject UUID (claim sub)"},"email":{"type":"string"},"firstName":{"type":"string","description":"Given name (Keycloak claim: given_name)."},"lastName":{"type":"string","description":"Family name / surname (Keycloak claim: family_name)."},"preferredUsername":{"type":"string","description":"Display-only username from preferred_username claim"},"roles":{"type":"array","description":"Realm roles without ROLE_ prefix","items":{"type":"string"}}},"required":["email","firstName","lastName","preferredUsername","roles","sub"]},"AdminApplicationResponseDto":{"type":"object","properties":{"applicantId":{"type":"string","format":"uuid","description":"Local id of the applicant"},"applicantKeycloakId":{"type":"string","description":"Keycloak id of the applicant"},"application":{"$ref":"#/components/schemas/ApplicationResponseDto"}},"required":["applicantId","applicantKeycloakId","application"]},"PageAdminApplicationResponseDto":{"type":"object","properties":{"totalElements":{"type":"integer","format":"int64"},"totalPages":{"type":"integer","format":"int32"},"size":{"type":"integer","format":"int32"},"content":{"type":"array","items":{"$ref":"#/components/schemas/AdminApplicationResponseDto"}},"number":{"type":"integer","format":"int32"},"numberOfElements":{"type":"integer","format":"int32"},"pageable":{"$ref":"#/components/schemas/PageableObject"},"sort":{"$ref":"#/components/schemas/SortObject"},"first":{"type":"boolean"},"last":{"type":"boolean"},"empty":{"type":"boolean"}}}}}}
